{
  "meta": {
    "id": "koichi.pack.dinosaurs",
    "name": "恐竜ずかん",
    "icon": "🦖",
    "themeColor": "#3f8a4d",
    "type": "user",
    "version": "1.0.0",
    "author": "コーイチ"
  },
  "categories": [
    { "id": "cat0", "label": "肉食恐竜", "color": "#c0392b" },
    { "id": "cat1", "label": "草食恐竜", "color": "#27ae60" }
  ],
  "records": [
    {
      "id": "rec_dino1",
      "title": "ティラノサウルス・レックス",
      "yomi": "てぃらのさうるす",
      "subtitle": "暴君トカゲの王",
      "summary": "史上最大級の肉食恐竜で、名前は「暴君トカゲの王」の意味。鋭い歯と強力なあごを持ち、白亜紀末の北米に生息していました。恐竜といえばコレ、という代名詞的な存在です。",
      "cat": "cat0",
      "catLabel": "肉食恐竜",
      "tags": ["肉食", "白亜紀"],
      "images": [],
      "links": []
    },
    {
      "id": "rec_dino2",
      "title": "ヴェロキラプトル",
      "yomi": "う゛ぇろきらぷとる",
      "subtitle": "すばしっこい狩人",
      "summary": "体長2mほどの小型の肉食恐竜。後ろ足の大きなかぎ爪と高い知能を持ち、すばやく走って狩りをしたと考えられています。羽毛があった可能性も指摘されています。",
      "cat": "cat0",
      "catLabel": "肉食恐竜",
      "tags": ["肉食", "小型"],
      "images": [],
      "links": []
    },
    {
      "id": "rec_dino3",
      "title": "トリケラトプス",
      "yomi": "とりけらとぷす",
      "subtitle": "3本の角を持つ守りの名手",
      "summary": "顔の3本の角と、首を守る大きな襟飾り（フリル）が特徴の草食恐竜。天敵に立ち向かうときにこの角とフリルを使ったとされます。がっしりした体つきも魅力です。",
      "cat": "cat1",
      "catLabel": "草食恐竜",
      "tags": ["草食", "角竜"],
      "images": [],
      "links": []
    }
  ]
}
